xpathparser.py
xpathparser-1.0.0.dist-info/DESCRIPTION.rst
xpathparser-1.0.0.dist-info/METADATA
xpathparser-1.0.0.dist-info/RECORD
xpathparser-1.0.0.dist-info/WHEEL
xpathparser-1.0.0.dist-info/metadata.json
xpathparser-1.0.0.dist-info/top_level.txt
